envsmtp/__init__.py
envsmtp-0.0.2.dist-info/LICENSE
envsmtp-0.0.2.dist-info/METADATA
envsmtp-0.0.2.dist-info/WHEEL
envsmtp-0.0.2.dist-info/top_level.txt
envsmtp-0.0.2.dist-info/RECORD
